{
  "schema_version": "market_cache.v0.1",
  "generated_at": "2026-06-08T00:00:00Z",
  "source": "coingecko_simple_price",
  "assets": {
    "btc_usd": {
      "price": 63533.0,
      "source": "coingecko bitcoin",
      "label": "BTC/USD spot",
      "provider": "coingecko",
      "as_of": "2026-06-08T16:55:29Z"
    },
    "gold_usd": {
      "price": 4332.55,
      "source": "pax-gold proxy",
      "label": "pax-gold proxy",
      "provider": "coingecko",
      "as_of": "2026-06-08T16:55:28Z"
    }
  },
  "errors": [],
  "metadata": {
    "as_of": "2026-06-08",
    "updated_assets": 2,
    "preserved_assets": 0,
    "error_count": 0
  }
}
